BuildANodeJsProjectFromScratch/README.md
BuildANodeJsProjectFromScratch/__init__.py
BuildANodeJsProjectFromScratch/__main__.py
BuildANodeJsProjectFromScratch/file.epub
BuildANodeJsProjectFromScratch/index.html
BuildANodeJsProjectFromScratch/css/__init__.py
BuildANodeJsProjectFromScratch/css/annotations.css
BuildANodeJsProjectFromScratch/css/main.css
BuildANodeJsProjectFromScratch/css/normalize.css
BuildANodeJsProjectFromScratch/css/popup.css
BuildANodeJsProjectFromScratch/font/__init__.py
BuildANodeJsProjectFromScratch/font/fontello.eot
BuildANodeJsProjectFromScratch/font/fontello.svg
BuildANodeJsProjectFromScratch/font/fontello.ttf
BuildANodeJsProjectFromScratch/font/fontello.woff
BuildANodeJsProjectFromScratch/img/__init__.py
BuildANodeJsProjectFromScratch/img/annotator-glyph-sprite.png
BuildANodeJsProjectFromScratch/img/annotator-icon-sprite.png
BuildANodeJsProjectFromScratch/img/apple-touch-icon.png
BuildANodeJsProjectFromScratch/img/cancelfullscreen.png
BuildANodeJsProjectFromScratch/img/close.png
BuildANodeJsProjectFromScratch/img/fullscreen.png
BuildANodeJsProjectFromScratch/img/loader.gif
BuildANodeJsProjectFromScratch/img/menu-icon.png
BuildANodeJsProjectFromScratch/img/save.png
BuildANodeJsProjectFromScratch/img/saved.png
BuildANodeJsProjectFromScratch/img/settings-s.png
BuildANodeJsProjectFromScratch/img/settings.png
BuildANodeJsProjectFromScratch/img/star.png
BuildANodeJsProjectFromScratch/js/__init__.py
BuildANodeJsProjectFromScratch/js/epub.js
BuildANodeJsProjectFromScratch/js/epub.min.js
BuildANodeJsProjectFromScratch/js/epub.min.map
BuildANodeJsProjectFromScratch/js/hooks.min.js
BuildANodeJsProjectFromScratch/js/hooks.min.map
BuildANodeJsProjectFromScratch/js/reader.js
BuildANodeJsProjectFromScratch/js/reader.js.map
BuildANodeJsProjectFromScratch/js/reader.min.js
BuildANodeJsProjectFromScratch/js/reader.min.map
BuildANodeJsProjectFromScratch/js/hooks/__init__.py
BuildANodeJsProjectFromScratch/js/hooks/extensions/__init__.py
build_a_node_js_project_from_scratch-2024.3.4.0.dist-info/METADATA
build_a_node_js_project_from_scratch-2024.3.4.0.dist-info/WHEEL
build_a_node_js_project_from_scratch-2024.3.4.0.dist-info/entry_points.txt
build_a_node_js_project_from_scratch-2024.3.4.0.dist-info/top_level.txt
build_a_node_js_project_from_scratch-2024.3.4.0.dist-info/RECORD
